pretty_print_dmeurer/__init__.py
pretty_print_dmeurer-1.2.1.dist-info/METADATA
pretty_print_dmeurer-1.2.1.dist-info/WHEEL
pretty_print_dmeurer-1.2.1.dist-info/licenses/LICENSE
pretty_print_dmeurer-1.2.1.dist-info/RECORD
